wft/__init__.py
wft/callbacks.py
wft/finetuner.py
wft/prepare_dataset.py
wft/utils.py
wft-0.0.8.dist-info/METADATA
wft-0.0.8.dist-info/WHEEL
wft-0.0.8.dist-info/licenses/LICENSE
wft-0.0.8.dist-info/RECORD
