Metadata-Version: 2.3
Name: wft
Version: 0.0.8
Summary: Run Whisper fine-tuning with ease.
Project-URL: Homepage, https://github.com/jacoblincool/wft
Project-URL: Issues, https://github.com/jacoblincool/wft/issues
Author-email: Jacob Lin <jacob@csie.cool>
License-File: LICENSE
Classifier: License :: OSI Approved :: MIT License
Classifier: Operating System :: OS Independent
Classifier: Programming Language :: Python :: 3
Requires-Python: >=3.10
Requires-Dist: accelerate
Requires-Dist: datasets>=3.0.0
Requires-Dist: evaluate
Requires-Dist: huggingface-hub
Requires-Dist: jiwer
Requires-Dist: librosa
Requires-Dist: peft
Requires-Dist: soundfile
Requires-Dist: tensorboard
Requires-Dist: torch>=2.0.0
Requires-Dist: transformers>=4.0.0
